MANIFEST.in
README.md
VERSION
setup.py
raspberrysystem/__init__.py
raspberrysystem/__main__.py
raspberrysystem/camera.py
raspberrysystem/ip.py
raspberrysystem.egg-info/PKG-INFO
raspberrysystem.egg-info/SOURCES.txt
raspberrysystem.egg-info/dependency_links.txt
raspberrysystem.egg-info/entry_points.txt
raspberrysystem.egg-info/not-zip-safe
raspberrysystem.egg-info/top_level.txt