Metadata-Version: 1.0
Name: raspberrysystem
Version: 0.2.3
Summary: The funniest joke in the world
Home-page: http://github.com/raubreywhite/raspberrysystem
Author: Richard
Author-email: w@rwhite.no
License: MIT
Platform: UNKNOWN
